{
  "prefs": {
    "DismissedWarpAIWarmWelcome": "true",
    "SystemTheme": "false",
    "AIAssistantRequestLimitInfo": "{\"limit\":100,\"num_requests_used_since_refresh\":0,\"next_refresh_time\":\"2024-02-23T17:46:14.287253Z\"}",
    "RestoreSession": "true",
    "Notifications": "{\"mode\":\"Enabled\",\"is_long_running_enabled\":true,\"long_running_threshold\":{\"secs\":30,\"nanos\":0},\"is_password_prompt_enabled\":true}",
    "Spacing": "\"Compact\"",
    "TelemetryEnabled": "false",
    "AutosuggestionAcceptedCount": "2",
    "ChangelogVersions": "{\"v0.2024.02.20.08.01.stable_01\":true,\"v0.2024.02.20.08.01.stable_02\":true,\"v0.2024.02.27.08.01.stable_03\":true,\"v0.2024.03.05.08.02.stable_00\":true}",
    "OpenWindowsAtCustomSize": "false",
    "AliasExpansionBannerSeen": "true",
    "WelcomeTipsFeaturesUsed": "[{\"Action\":\"SplitPane\"},{\"Hint\":\"CreateBlock\"},{\"Hint\":\"BlockSelect\"},{\"Hint\":\"BlockAction\"},{\"Action\":\"WarpAI\"},{\"Action\":\"CommandPalette\"},{\"Action\":\"ThemePicker\"},{\"Action\":\"OpenWarpDrive\"}]",
    "Shortcuts": "true",
    "ShouldDimInactivePanes": "true",
    "WorkflowsBoxOpen": "true",
    "ExperimentId": "5f8a1f53-8afe-4cb4-9485-39fee55021c0",
    "HasAutoOpenedWelcomeFolder": "true",
    "CrashReportingEnabled": "true",
    "HonorPS1": "true",
    "PreferMarkdownViewer": "true",
    "WorkingDirectoryConfig": "{\"advanced_mode\":false,\"global\":{\"mode\":\"HomeDir\",\"custom_dir\":\"\"},\"split_pane\":{\"mode\":\"PreviousDir\",\"custom_dir\":\"\"},\"new_tab\":{\"mode\":\"PreviousDir\",\"custom_dir\":\"\"},\"new_window\":{\"mode\":\"PreviousDir\",\"custom_dir\":\"\"}}",
    "FontSize": "15.0",
    "HasDismissedWarpDriveWelcome": "true",
    "ReceivedReferralTheme": "\"Inactive\"",
    "WelcomeTipsCompleted": "true",
    "Theme": "{\"Custom\":{\"name\":\"Taerminal\",\"path\":\"/home/david/.local/share/warp-terminal/themes/standard/taerminal.yaml\"}}"
  }
}